getactivewindow/__init__.py
getactivewindow/py.typed
getactivewindow_x-0.4.0.dist-info/LICENSE
getactivewindow_x-0.4.0.dist-info/METADATA
getactivewindow_x-0.4.0.dist-info/WHEEL
getactivewindow_x-0.4.0.dist-info/top_level.txt
getactivewindow_x-0.4.0.dist-info/zip-safe
getactivewindow_x-0.4.0.dist-info/RECORD
