Metadata-Version: 2.2
Name: getactivewindow_x
Version: 0.4.0
Summary: Separate component to get information on the active window in X.
Home-page: https://github.com/user202729/getactivewindow-x
Author: user202729
License: GNU General Public License v3 or later (GPLv3+)
Classifier: Environment :: Plugins
Classifier: License :: OSI Approved :: GNU General Public License v3 or later (GPLv3+)
Classifier: Operating System :: OS Independent
Classifier: Programming Language :: Python :: 3
License-File: LICENSE
Requires-Dist: python-xlib~=0.29
Requires-Dist: ewmh~=0.1.6
